<?xml version="1.0"?>
<Game>
    <Level>
		<LevelId>1</LevelId>
        <SpriteCount>4</SpriteCount>
        <Sprite>
			<Name>Content/gravity_normal</Name>
            <SpriteType>GRAVITY_UP</SpriteType>
            <Position>
                <X>1400</X>
                <Y>200</Y>
            </Position>            
        </Sprite>
        <Sprite>
			<Name>Content/gravity_upsidedown</Name>
            <SpriteType>GRAVITY_DOWN</SpriteType>
            <Position>
              <X>300</X>
                <Y>900</Y>
            </Position>            
        </Sprite>

      <Sprite>
        <Name>Content/mario</Name>
        <SpriteType>ENEMY</SpriteType>
        <Position>
          <X>300</X>
          <Y>800</Y>
        </Position>
		<Animation>
			<SizeX>100</SizeX>
			<SizeY>100</SizeY>
			<Frames>1</Frames>
      </Animation>
      </Sprite>
    <Sprite>
      <Name>Content/chodz</Name>
      <SpriteType>PLAYER</SpriteType>
      <Position>
        <X>150</X>
        <Y>800</Y>
      </Position>
      <Animation>
        <SizeX>95</SizeX>
        <SizeY>157</SizeY>
        <Frames>13</Frames>
      </Animation>
      </Sprite>
		<TileMap>
			<FileName>Content/level_1.tmx</FileName>
			<FileSet>Content/spritesheet</FileSet>
		</TileMap>
		<SoundEffect>Content/jump</SoundEffect>
		<Song>Content/backgroundMusic</Song>
    </Level>
  <Level>
    <LevelId>2</LevelId>
        <SpriteCount>4</SpriteCount>
        <Sprite>
			<Name>Content/gravity_normal</Name>
            <SpriteType>GRAVITY_UP</SpriteType>
            <Position>
                <X>1400</X>
                <Y>200</Y>
            </Position>            
        </Sprite>
        <Sprite>
			<Name>Content/gravity_upsidedown</Name>
            <SpriteType>GRAVITY_DOWN</SpriteType>
            <Position>
              <X>300</X>
                <Y>900</Y>
            </Position>            
        </Sprite>

      <Sprite>
        <Name>Content/mario</Name>
        <SpriteType>BOX</SpriteType>
        <Position>
          <X>300</X>
          <Y>800</Y>
        </Position>
		<Animation>
			<SizeX>100</SizeX>
			<SizeY>100</SizeY>
			<Frames>1</Frames>
      </Animation>
      </Sprite>
    <Sprite>
      <Name>Content/chodz</Name>
      <SpriteType>PLAYER</SpriteType>
      <Position>
        <X>150</X>
        <Y>800</Y>
      </Position>
      <Animation>
        <SizeX>95</SizeX>
        <SizeY>157</SizeY>
        <Frames>13</Frames>
      </Animation>
      </Sprite>
		<TileMap>
			<FileName>Content/level_2.tmx</FileName>
			<FileSet>Content/spritesheet</FileSet>
		</TileMap>
		<SoundEffect>Content/jump</SoundEffect>
		<Song>Content/backgroundMusic</Song>
    </Level>
</Game>